brokrpc/__init__.py
brokrpc/abc.py
brokrpc/broker.py
brokrpc/builder.py
brokrpc/cli.py
brokrpc/consumer.py
brokrpc/debug.py
brokrpc/driver/__init__.py
brokrpc/driver/aiormq.py
brokrpc/driver/memory.py
brokrpc/message.py
brokrpc/middleware.py
brokrpc/model.py
brokrpc/options.py
brokrpc/plugin.py
brokrpc/publisher.py
brokrpc/py.typed
brokrpc/queue.py
brokrpc/retry.py
brokrpc/rpc/__init__.py
brokrpc/rpc/abc.py
brokrpc/rpc/caller.py
brokrpc/rpc/client.py
brokrpc/rpc/handler.py
brokrpc/rpc/model.py
brokrpc/rpc/server.py
brokrpc/rpc/storage.py
brokrpc/serializer/__init__.py
brokrpc/serializer/ident.py
brokrpc/serializer/json.py
brokrpc/serializer/protobuf.py
brokrpc/serializer/pydantic.py
brokrpc/serializer/raw.py
brokrpc/spec/__init__.py
brokrpc/spec/v1/__init__.py
brokrpc/spec/v1/amqp_pb2.py
brokrpc/spec/v1/amqp_pb2.pyi
brokrpc/spec/v1/call_pb2.py
brokrpc/spec/v1/call_pb2.pyi
brokrpc/spec/v1/consumer_pb2.py
brokrpc/spec/v1/consumer_pb2.pyi
brokrpc/stringify.py
brokrpc-0.3.0.dist-info/LICENSE
brokrpc-0.3.0.dist-info/METADATA
brokrpc-0.3.0.dist-info/WHEEL
brokrpc-0.3.0.dist-info/entry_points.txt
brokrpc-0.3.0.dist-info/RECORD
