Metadata-Version: 2.3
Name: BrokRPC
Version: 0.3.0
Summary: framework for gRPC like server-client communication over message brokers
License: MIT
Keywords: python,protobuf,amqp,grpc,message-queue,message-broker
Author: zerlok
Author-email: danil.troshnev@gmail.com
Requires-Python: >=3.12,<4.0
Classifier: Development Status :: 1 - Planning
Classifier: Intended Audience :: Developers
Classifier: License :: OSI Approved :: MIT License
Classifier: Operating System :: OS Independent
Classifier: Programming Language :: Python :: 3
Classifier: Programming Language :: Python :: 3.12
Classifier: Programming Language :: Python :: 3.13
Classifier: Topic :: Software Development :: Libraries :: Application Frameworks
Classifier: Topic :: System :: Networking
Classifier: Typing :: Typed
Provides-Extra: aiormq
Provides-Extra: cli
Provides-Extra: protobuf
Provides-Extra: pydantic
Requires-Dist: aiofiles (>=24.1.0,<25.0.0) ; extra == "cli"
Requires-Dist: aiormq (>=6.8.1,<7.0.0) ; extra == "aiormq"
Requires-Dist: googleapis-common-protos (>=1.65.0,<2.0.0) ; extra == "protobuf"
Requires-Dist: protobuf (>=5.26.1,<6.0.0) ; extra == "protobuf"
Requires-Dist: pydantic (>=2.10.4,<3.0.0) ; extra == "pydantic"
Requires-Dist: yarl (>=1.18.0,<2.0.0)
Project-URL: Homepage, https://github.com/zerlok/BrokRPC
Project-URL: Issues, https://github.com/zerlok/BrokRPC/issues
